vidformer/__init__.py
vidformer/cv2/__init__.py
vidformer/supervision/__init__.py
vidformer-1.3.0.dist-info/WHEEL
vidformer-1.3.0.dist-info/METADATA
vidformer-1.3.0.dist-info/RECORD
