Metadata-Version: 2.4
Name: vidformer
Version: 1.3.0
Summary: vidformer-py is a Python 🐍 interface for [vidformer](https://github.com/ixlab/vidformer).
Author-email: Dominik Winecki <dominikwinecki@gmail.com>
Requires-Python: >=3.8
Classifier: Programming Language :: Python :: 3
Classifier: Operating System :: OS Independent
Requires-Dist: requests
Requires-Dist: numpy
Project-URL: Documentation, https://ixlab.github.io/vidformer/vidformer-py/
Project-URL: Homepage, https://ixlab.github.io/vidformer/
Project-URL: Issues, https://github.com/ixlab/vidformer/issues
